odoo/addons/oca_custom/README.rst
odoo/addons/oca_custom/__init__.py
odoo/addons/oca_custom/__manifest__.py
odoo/addons/oca_custom/models/__init__.py
odoo/addons/oca_custom/models/res_partner.py
odoo/addons/oca_custom/readme/CONTRIBUTORS.rst
odoo/addons/oca_custom/readme/DESCRIPTION.rst
odoo/addons/oca_custom/static/description/icon.png
odoo/addons/oca_custom/static/description/index.html
odoo/addons/oca_custom/views/res_partner.xml
odoo14_addon_oca_custom-14.0.1.0.0.dist-info/METADATA
odoo14_addon_oca_custom-14.0.1.0.0.dist-info/WHEEL
odoo14_addon_oca_custom-14.0.1.0.0.dist-info/top_level.txt
odoo14_addon_oca_custom-14.0.1.0.0.dist-info/RECORD
