Metadata-Version: 2.1
Name: odoo14-addon-oca-custom
Version: 14.0.1.0.0
Summary: Custom Settings for OCA Instance
Home-page: https://github.com/OCA/oca-custom
Author: GRAP, Akretion, Odoo Community Association (OCA)
Author-email: support@odoo-community.org
License: AGPL-3
Platform: UNKNOWN
Classifier: Programming Language :: Python
Classifier: Framework :: Odoo
Classifier: License :: OSI Approved :: GNU Affero General Public License v3
Requires-Python: >=3.6
Requires-Dist: odoo14-addon-github-connector
Requires-Dist: odoo (<14.1dev,>=14.0a)
